{
  "replace": [
    {
      "find": "R-PROJECT-NAME",
      "description": "What's the name of your project? Something suitable for ___.xcodeproj",
      "accept": "[a-zA-Z0-9_-]",
      "suggestion": "folder.name"
    },
    {
      "find": "R-PROJECT-DISPLAY-NAME",
      "description": "What's the display name of your project (as seen on homescreen)?",
      "suggestion": "R-PROJECT-NAME"
    },
    {
      "find": "R-AUTHOR-NAME",
      "description": "What's your name?",
      "suggestion": "git.user.name"
    },
    {
      "find": "R-AUTHOR-EMAIL",
      "description": "What's your email address?",
      "suggestion": "git.user.email"
    },
    {
      "find": "R-COMPANY-NAME",
      "description": "What's your company name?"
    },
    {
      "find": "R-BUNDLE-IDENTIFIER",
      "description": "What's your bundle identifier? E.g. \"no.agens.gearbox\""
    }
  ]
}
